[{"children": [{"children": [{"children": [{"resource-id": "mendeleev.redlime:id/action_bar_root", "bounds": "[0,0][1200,1972]", "children": [{"resource-id": "android:id/content", "bounds": "[0,0][1200,1972]", "children": [{"scrollable": "true", "bounds": "[0,0][1200,1972]", "count": 0, "children": [{"resource-id": "mendeleev.redlime:id/appbar", "bounds": "[0,0][1200,696]", "children": [{"resource-id": "mendeleev.redlime:id/proHeaderContainer", "bounds": "[0,0][1200,696]", "children": [{"resource-id": "mendeleev.redlime:id/backgroundGradient", "bounds": "[0,0][1200,696]"}, {"resource-id": "mendeleev.redlime:id/statusBarHack", "bounds": "[0,0][1200,66]"}, {"resource-id": "mendeleev.redlime:id/g1", "bounds": "[0,123][1200,692]"}, {"clickable": "true", "content": "mendeleev.redlime:id/backBtn \u8fd4\u56de\u4e0a\u4e00\u5c4f\u5e55 ", "bounds": "[14,99][84,169]", "count": 1}, {"resource-id": "mendeleev.redlime:id/backgroundImage", "bounds": "[885,0][1200,315]"}, {"text": "\u5143\u7d20\u5468\u671f\u8868", "bounds": "[35,534][1032,605]", "resource-id": "mendeleev.redlime:id/title"}, {"text": "Professional", "bounds": "[35,612][236,661]", "resource-id": "mendeleev.redlime:id/professionalTv"}, {"clickable": "true", "content": "mendeleev.redlime:id/goProBtn ", "bounds": "[1060,556][1165,661]", "count": 2}]}]}, {"scrollable": "true", "bounds": "[0,696][1200,1972]", "count": 3, "resource-id": "mendeleev.redlime:id/list", "children": [{"children": [{"children": [{"resource-id": "mendeleev.redlime:id/icon", "bounds": "[35,759][81,805]"}, {"children": [{"text": "\u8ba1\u7b97\u5668\uff1a", "bounds": "[116,731][248,775]", "resource-id": "mendeleev.redlime:id/title"}, {"text": "\u7b80\u5355\u5feb\u901f\u7684\u8ba1\u7b97\u5668\uff0c\u7528\u4e8e\u8ba1\u7b97\u6469\u5c14\u8d28\u91cf\uff0c\u65b9\u4fbf\u8f93\u5165\u4efb\u4f55\u590d\u6742\u7684\u516c\u5f0f", "bounds": "[116,789][841,823]", "resource-id": "mendeleev.redlime:id/descriptionTv"}]}]}, {}]}, {"children": [{"children": [{"resource-id": "mendeleev.redlime:id/icon", "bounds": "[35,923][81,969]"}, {"children": [{"text": "\u7269\u54c1\u6e05\u5355\uff1a", "bounds": "[116,895][281,939]", "resource-id": "mendeleev.redlime:id/title"}, {"text": "\u9879\u76ee\u5217\u8868\u4e2d\u5c5e\u6027\u7684\u53ef\u89c6\u5316\u663e\u793a\u65e2\u7f8e\u89c2\u53c8\u65b9\u4fbf\uff01", "bounds": "[116,953][616,987]", "resource-id": "mendeleev.redlime:id/descriptionTv"}]}]}, {}]}, {"children": [{"children": [{"resource-id": "mendeleev.redlime:id/icon", "bounds": "[35,1087][81,1133]"}, {"children": [{"text": "\u4e13\u4e1a\u672f\u8bed\uff1a", "bounds": "[116,1059][281,1103]", "resource-id": "mendeleev.redlime:id/title"}, {"text": "\u5316\u5b66\u8bcd\u6c47\u8868\n \u89e3\u9501\u5927\u91cf\u975e\u5e38\u91cd\u8981\u7684\u5316\u5b66\u672f\u8bed - \u53ea\u9700\u6253\u5f00\u201c\u8bcd\u6c47\u8868\u201d\u90e8\u5206", "bounds": "[116,1117][713,1185]", "resource-id": "mendeleev.redlime:id/descriptionTv"}]}]}, {}]}, {"children": [{"children": [{"resource-id": "mendeleev.redlime:id/icon", "bounds": "[35,1285][81,1331]"}, {"children": [{"text": "\u7b14\u8bb0\uff1a", "bounds": "[116,1257][215,1301]", "resource-id": "mendeleev.redlime:id/title"}, {"text": "\u80fd\u591f\u7f16\u8f91\u5316\u5b66\u5143\u7d20\u7684\u6ce8\u91ca\u5e76\u5728\u4f7f\u7528\u5143\u7d20\u65f6\u8f93\u5165\u60a8\u7684\u4fe1\u606f", "bounds": "[116,1315][716,1349]", "resource-id": "mendeleev.redlime:id/descriptionTv"}]}]}, {}]}, {"children": [{"children": [{"resource-id": "mendeleev.redlime:id/icon", "bounds": "[35,1449][81,1495]"}, {"children": [{"text": "\u66f4\u591a\u4fe1\u606f\uff1a", "bounds": "[116,1421][281,1465]", "resource-id": "mendeleev.redlime:id/title"}, {"text": "\u89e3\u9501\u5173\u4e8e\u5143\u7d20\u7684\u66f4\u591a\u4fe1\u606f\n \u60a8\u53ef\u4ee5\u4e86\u89e3\u66f4\u591a\u6709\u8da3\u7684\u4fe1\u606f\uff0c\u4f8b\u5982\uff1a\n - \u539f\u5b50\u6838\u6027\u8d28\n- \u53cd\u5e94\u6d3b\u6027\n- \u7535\u78c1\u6027\u8d28\n- \u539f\u5b50\u6027\u8d28\n- \u70ed\u529b\u5b66\u6027\u8d28\n- \u540c\u4f4d\u7d20\n- \u534a\u8870\u671f\n- \u6469\u5c14\u4f53\u79ef\n \u66f4\u591a\u4fe1\u606f\uff0c\u5c3d\u5728\u4e13\u4e1a\u7248", "bounds": "[116,1479][523,1853]", "resource-id": "mendeleev.redlime:id/descriptionTv"}]}]}, {}]}, {"children": [{"children": [{"resource-id": "mendeleev.redlime:id/icon", "bounds": "[35,1953][81,1972]"}, {"children": [{"text": "\u5f3a\u5927\u7684\u641c\u7d22\uff1a", "bounds": "[116,1925][314,1969]", "resource-id": "mendeleev.redlime:id/title"}]}]}]}]}, {"clickable": "true", "content": "mendeleev.redlime:id/btnFooter Google Play ", "bounds": "[28,1821][1172,1965]", "count": 4}]}]}]}]}]}, {"resource-id": "android:id/statusBarBackground", "bounds": "[0,0][1200,66]"}, {"resource-id": "android:id/navigationBarBackground", "bounds": "[0,0][0,0]"}]}]